mcp_server_if/py.typed
mcp_server_if/__main__.py
mcp_server_if/__init__.py
mcp_server_if/server.py
mcp_server_if/config.py
mcp_server_if/session.py
mcp_server_if/bin/glulxe
mcp_server_if-0.1.0.dist-info/WHEEL
mcp_server_if-0.1.0.dist-info/entry_points.txt
mcp_server_if-0.1.0.dist-info/METADATA
mcp_server_if-0.1.0.dist-info/RECORD
mcp_server_if-0.1.0.dist-info/licenses/LICENSE
