Metadata-Version: 2.4
Name: mcp-server-if
Version: 0.1.0
Summary: MCP server for playing Glulx interactive fiction games
Project-URL: Homepage, https://github.com/davidar/mcp-server-if
Project-URL: Repository, https://github.com/davidar/mcp-server-if
Project-URL: Issues, https://github.com/davidar/mcp-server-if/issues
Author-email: David A Roberts <d@vidr.cc>
License-Expression: MIT
License-File: LICENSE
Keywords: claude,glulx,interactive-fiction,mcp,text-adventure
Classifier: Development Status :: 4 - Beta
Classifier: Intended Audience :: Developers
Classifier: License :: OSI Approved :: MIT License
Classifier: Programming Language :: Python :: 3
Classifier: Programming Language :: Python :: 3.10
Classifier: Programming Language :: Python :: 3.11
Classifier: Programming Language :: Python :: 3.12
Classifier: Programming Language :: Python :: 3.13
Classifier: Topic :: Games/Entertainment :: Role-Playing
Requires-Python: >=3.10
Requires-Dist: httpx>=0.25.0
Requires-Dist: mcp>=1.0.0
